imageInterfusion/__init__.py
imageInterfusion/interfusion/__init__.py
imageInterfusion/interfusion/imageFit.py
imageInterfusion/interfusion/imageMerge.py
imageInterfusion/useful/__init__.py
imageInterfusion/useful/io.py
imageInterfusion/useful/plot.py
imageInterfusion-0.0.1.dist-info/METADATA
imageInterfusion-0.0.1.dist-info/WHEEL
imageInterfusion-0.0.1.dist-info/top_level.txt
imageInterfusion-0.0.1.dist-info/RECORD
