Metadata-Version: 2.1
Name: imageInterfusion
Version: 0.0.1
Summary: Image processing Package using skimage
Home-page: https://github.com/NetoAluizio/image-interfusion-package
Author: Aluizio
License: UNKNOWN
Platform: UNKNOWN
Requires-Python: >=3.5
Requires-Dist: matplotlib
Requires-Dist: numpy
Requires-Dist: scikit-image (>=0.16.1)
